jugaad_data/__init__.py
jugaad_data/cli.py
jugaad_data/holidays.py
jugaad_data/util.py
jugaad_data/bse/__init__.py
jugaad_data/bse/live.py
jugaad_data/nse/__init__.py
jugaad_data/nse/archives.py
jugaad_data/nse/history.py
jugaad_data/nse/live.py
jugaad_data/rbi/__init__.py
jugaad_data-0.28.dist-info/licenses/LICENSE.YOLO.md
jugaad_data-0.28.dist-info/METADATA
jugaad_data-0.28.dist-info/WHEEL
jugaad_data-0.28.dist-info/entry_points.txt
jugaad_data-0.28.dist-info/top_level.txt
jugaad_data-0.28.dist-info/RECORD
