Metadata-Version: 2.4
Name: jugaad-data
Version: 0.28
Summary: Free Zerodha API python library
Author-email: jugaad-coder <abc@xyz.com>
License: YOLO
Project-URL: Homepage, https://marketsetup.in/documentation/jugaad-data/
Project-URL: Documentation, https://marketsetup.in/documentation/jugaad-data/
Project-URL: Repository, https://github.com/jugaad-py/jugaad-data
Project-URL: Issues, https://github.com/jugaad-py/jugaad-data/issues
Keywords: NSE,Live,Bhavcopy,History,Futures,Options,Stock Data
Requires-Python: >=3.6
License-File: LICENSE.YOLO.md
Requires-Dist: requests
Requires-Dist: click==7.1.2
Requires-Dist: appdirs==1.4.4
Requires-Dist: beautifulsoup4==4.9.3
Dynamic: license-file
